{
  "data": {
    "id": 2,
    "name": "CHINESE TEA TOOL SET 6IN1 BAMBU SENDOK PINSET TEH CHINA - PERLENGKAPAN TEH CHINA KERAJINAN BAMBU",
    "imageUrl": "https://s0.bukalapak.com/img/57853414192/large/data.png.webp",
    "price": 70000,
    "originalPrice": 100000,
    "percentDiscount": 30,
    "rating": 4.9,
    "soldCount": 24,
    "shopName": "Toko Maju Jaya",
    "condition": "Baru",
    "dimension": "10 gram",
    "minOrder": "1 Buah",
    "category": "Elektronik",
    "description": "Beli aneka produk di Toko Gondray store secara online sekarang. Kamu bisa beli produk dari Toko Gondray store dengan aman &amp; mudah dari Kota Bekasi. Ingin belanja lebih hemat &amp; terjangkau di Toko Gondray store?"
  }
}